Workbook

Sheet 1_PROGRESS PAYMENT
B5: Subcontract Payment Request | H5: SIGN | I5: IN CHARGE | J5: CONS DEPT. | K5: PLN DEPT. | M5: P.M
I7: / / | J7: / / | K7: / / | M7: / /
B10: INVOICE DATE | E10: INVOICE NO | F10: =IF(OR('1_PROGRESS PAYMENT'!$H$12="",'1_PROGRESS PAYMENT'!$C$38=""),"",'1_PROGRESS PAYMENT'!$H$12&"-INV-"&TEXT('1_PROGRESS PAYMENT'!$C$38,"000")) | I10: DUE DATE | M10: ADMIN DEPT.
B12: PROJECT | C12: HL-GA Battery Project | F12: CONTRACT NUMBER
B13: SUBCONTRACTOR | C13: Nahshon MEP | F13: CONTRACT PRICE | H13: ='3_CONTINUATION SHEET'!K41 -> 1789000
B14: SCOPE OF WORKS | C14: Additional Finish Works PKG-7 | F14: P/BOND AMT/EXPIRY | M14: FNC DEPT.
B15: CONTRACT PERIOD | C15: 2026.08 ~ 2026.11 | D15: CONTRACT DATE | F15: AP-BOND AMT/EXPIRY
B16: INSURANCE | F16: W-BOND AMT/EXPIRY
I17: ( Currency : USD )
B18: DESCRIPTION | E18: UP TO PREVIOUS BILL | F18: THIS BILL | G18: UP TO THIS BILL | J18: REMARKS
B19: PAYMENT RECEIVED IN ADVANCE | D19: ① | E19: 0 | F19: =IF(OR(NOT(ISNUMBER(G19)),NOT(ISNUMBER(E19))),"",G19-E19) -> 357800 | G19: 357800 | J19: 0.2
B20: WORKS DONE | C20: WORK DONE | E20: =IF(NOT(ISNUMBER('3_CONTINUATION SHEET'!M41)),"",'3_CONTINUATION SHEET'!M41) -> 0 | F20: =IF(OR(NOT(ISNUMBER(G20)),NOT(ISNUMBER(E20))),"",G20-E20) -> 218000 | G20: =IF(NOT(ISNUMBER('3_CONTINUATION SHEET'!Q41)),"",'3_CONTINUATION SHEET'!Q41) -> 218000 | J20: =IF(NOT(ISNUMBER(G20)),"",G20/H13) -> 0.12185579
C21: V/O, C/O | E21: 0 | F21: =IF(OR(NOT(ISNUMBER(G21)),NOT(ISNUMBER(E21))),"",G21-E21) -> 0 | G21: 0
C22: OTHERS | E22: 0 | F22: =IF(OR(NOT(ISNUMBER(G22)),NOT(ISNUMBER(E22))),"",G22-E22) -> 0 | G22: 0
C23: GROSS AMOUNT | D23: ② | E23: =IF(NOT(ISNUMBER(E20)),"",SUM(E20:E22)) -> 0 | F23: =IF(OR(NOT(ISNUMBER(G23)),NOT(ISNUMBER(E23))),"",G23-E23) -> 218000 | G23: =IF(NOT(ISNUMBER(G20)),"",SUM(G20:G22)) -> 218000 | H23: =H20+H21+H22 -> 0 | I23: =I20+I21+I22 -> 0
B24: ADV. REPAYMENT | C24: GROSS AMOUNT | D24: ③ | E24: 0 | F24: =IF(OR(NOT(ISNUMBER(G24)),NOT(ISNUMBER(E24))),"",G24-E24) -> 0 | G24: 0
B25: RETENTION | C25: =IF(OR(NOT(ISNUMBER('3_CONTINUATION SHEET'!U41)),NOT(ISNUMBER('3_CONTINUATION SHEET'!Q41)),'3_CONTINUATION SHEET'!Q41=0),0,'3_CONTINUATION SHEET'!U41/'3_CONTINUATION SHEET'!Q41) -> 0.05 | D25: ④ | E25: =IF(OR(NOT(ISNUMBER(E23)),NOT(ISNUMBER('1_PROGRESS PAYMENT'!$C$25))),"",IF(ISNUMBER('1_PROGRESS PAYMENT'!$H$41),'1_PROGRESS PAYMENT'!$H$41,ROUND(E23*'1_PROGRESS PAYMENT'!$C$25,2))) -> 0 | F25: =IF(OR(NOT(ISNUMBER(G25)),NOT(ISNUMBER(E25))),"",G25-E25) -> 10900 | G25: =IF(OR(NOT(ISNUMBER(G23)),NOT(ISNUMBER(C25))),"",ROUND(G23*C25,2)) -> 10900
B26: CONTRA CHARGES | C26: MATERIALS | E26: 0 | F26: =IF(OR(NOT(ISNUMBER(G26)),NOT(ISNUMBER(E26))),"",G26-E26) -> 0 | G26: 0
C27: LABOUR CHG | E27: 0 | F27: =IF(OR(NOT(ISNUMBER(G27)),NOT(ISNUMBER(E27))),"",G27-E27) -> 0 | G27: 0
C28: EQUIPMENT | E28: 0 | F28: =IF(OR(NOT(ISNUMBER(G28)),NOT(ISNUMBER(E28))),"",G28-E28) -> 0 | G28: 0
C29: OTHERS | E29: 0 | F29: =IF(OR(NOT(ISNUMBER(G29)),NOT(ISNUMBER(E29))),"",G29-E29) -> 0 | G29: 0
C30: SUB-TOTAL | D30: ⑤ | E30: =SUM(E26:E29) -> 0 | F30: =IF(OR(NOT(ISNUMBER(G30)),NOT(ISNUMBER(E30))),"",G30-E30) -> 0 | G30: =SUM(G26:G29) -> 0
B31: NET AMOUNT | D31: ⑥=①+②-③-④-⑤ | E31: =IF(OR(NOT(ISNUMBER(E23)),NOT(ISNUMBER(E25))),"",E19+E23-E24-E25-E30) -> 0 | F31: =IF(OR(NOT(ISNUMBER(G31)),NOT(ISNUMBER(E31))),"",G31-E31) -> 564900 | G31: =IF(OR(NOT(ISNUMBER(G23)),NOT(ISNUMBER(G25))),"",G19+G23-G24-G25-G30) -> 564900
B32: TAXES | D32: ⑦ | E32: 0 | F32: =IF(OR(NOT(ISNUMBER(G32)),NOT(ISNUMBER(E32))),"",G32-E32) -> 0 | G32: 0
C33: WITHHOLDING (less) | D33: ⑧ | E33: 0 | F33: =IF(OR(NOT(ISNUMBER(G33)),NOT(ISNUMBER(E33))),"",G33-E33) -> 0 | G33: 0
B34: NET RECEIPT | D34: ⑨=⑥+⑦-⑧ | E34: =IF(NOT(ISNUMBER(E31)),"",E31+E32-E33) -> 0 | F34: =IF(OR(NOT(ISNUMBER(G34)),NOT(ISNUMBER(E34))),"",G34-E34) -> 564900 | G34: =IF(NOT(ISNUMBER(G31)),"",G31+G32-G33) -> 564900
B36: =IF(NOT(ISNUMBER('3_CONTINUATION SHEET'!Q41)),"Check continuation sheet total.",IF(NOT(ISNUMBER(C25)),"Check retainage rate.",""))
B37: ADDITIONAL INPUTS (not printed on payment request)
B38: Application no. | F38: Period to
B39: Contractor address
F40: CCI job no.
F41: Previous retainage
B42: Previous retainage: leave blank to calculate from the current retainage rate; enter the approved prior amount to override.
B43: Progress %: enter previous cumulative in sheet 3 Q2, current cumulative in S2. Retainage %: C25 above.

Sheet 2_APPLICATION
A1: APPLICATION AND CERTIFICATE FOR PAYMENT
A2: TO GC | C2: =IF('1_PROGRESS PAYMENT'!$K$11="","",'1_PROGRESS PAYMENT'!$K$11) | F2: PROJECT: | G2: ='1_PROGRESS PAYMENT'!C12 -> HL-GA Battery Project | K2: APPLICATION #: | M2: =IF('1_PROGRESS PAYMENT'!$C$38="","",'1_PROGRESS PAYMENT'!$C$38)
K3: PERIOD TO: | M3: =IF('1_PROGRESS PAYMENT'!$H$38="","",'1_PROGRESS PAYMENT'!$H$38)
K4: CCI JOB #: | M4: =IF('1_PROGRESS PAYMENT'!$H$40="","",'1_PROGRESS PAYMENT'!$H$40)
K5: CONTRACT NO: | M5: =IF('1_PROGRESS PAYMENT'!$H$12="","",'1_PROGRESS PAYMENT'!$H$12)
K6: APPLICATION DATE: | M6: =IF('1_PROGRESS PAYMENT'!$C$10="","",'1_PROGRESS PAYMENT'!$C$10)
A7: FROM CONTRACTOR: | C7: =IF('1_PROGRESS PAYMENT'!$C$13="","",'1_PROGRESS PAYMENT'!$C$13) -> Nahshon MEP | K7: INVOICE #: | M7: =IF('1_PROGRESS PAYMENT'!$H$12="","",'1_PROGRESS PAYMENT'!F10)
C8: =IF('1_PROGRESS PAYMENT'!$C$39="","",'1_PROGRESS PAYMENT'!$C$39)
A13: CONTRACTOR'S APPLICATION FOR PAYMENT | G13: The undersigned Contractor certifies that to the best of the Contractor's knowledge,
A14: Application is made for payment, as shown below, in connection with the Contract. | G14: information and belief the Work covered by this Application for Payment has been
G15: completed in accordance with the Contract Documents, that all amounts have been
A16: 1 | B16: ORIGINAL CONTRACT SUM............................ | F16: ='3_CONTINUATION SHEET'!K41 -> 1789000 | G16: paid by the Contractor for Work for which previous Certificates for Payment were issued
G17: and payments received from the Owner, and that current payment shown herein is now due.
A18: 2 | B18: NET CHANGE BY CHANGE ORDERS............. | F18: 0
G19: Contractor: | H19: =IF('1_PROGRESS PAYMENT'!$C$13="","",'1_PROGRESS PAYMENT'!$C$13) -> Nahshon MEP
A20: 3 | B20: CONTRACT SUM TO DATE (LINE 1 & 2)......... | F20: =SUM(F16:F19) -> 1789000
G21: By: | L21: Date:
A22: 4 | B22: TOTAL COMPLETED & STORED TO DATE.... | F22: =IF(NOT(ISNUMBER('1_PROGRESS PAYMENT'!G23)),"",'1_PROGRESS PAYMENT'!G23) -> 218000 | G22: General Manager
G23: State of:
A24: 5 | B24: RETAINAGE: | G24: County of:
G25: Subscribed and sworn to before
B26: RETAINAGE ON COMPLETED WORK | E26: =IF(NOT(ISNUMBER('1_PROGRESS PAYMENT'!G25)),"",'1_PROGRESS PAYMENT'!G25) -> 10900 | G26: me this day of
B28: OTHER NET DEDUCTIONS / ADDITIONS | E28: ='1_PROGRESS PAYMENT'!G24+'1_PROGRESS PAYMENT'!G30+'1_PROGRESS PAYMENT'!G33-'1_PROGRESS PAYMENT'!G19-'1_PROGRESS PAYMENT'!G32 -> -357800 | G28: Notary Public:
G29: My Commission expires:
B30: TOTAL NET DEDUCTIONS | F30: =IF(NOT(ISNUMBER(E26)),"",SUM(E26,E28)) -> -346900
A32: 6 | B32: TOTAL EARNED LESS NET DEDUCTIONS | F32: =IF(OR(NOT(ISNUMBER(F22)),NOT(ISNUMBER(F30))),"",F22-F30) -> 564900 | G32: CERTIFICATE FOR PAYMENT
B33: (LINE 4 LESS LINE 5 TOTAL)
G34: In accordance with the Contract Documents, based on on-site observations and the data comprising
A35: 7 | B35: LESS PREVIOUS APPLICATIONS FOR PAYMENT | F35: =IF(NOT(ISNUMBER('1_PROGRESS PAYMENT'!E34)),"",'1_PROGRESS PAYMENT'!E34) -> 0 | G35: this application, the General Contractor certifies to the Owner that to the best of its knowledge,
B36: (LINE 6 FROM PRIOR CERTIFICATE) | G36: information and belief the work has progressed as indicated, the quality of the work is in accordance
G37: with the Contract Documents, and the Contractor is entitled to payment of the AMOUNT CERTIFIED.
A38: 8 | B38: CURRENT PAYMENT DUE......................................... | F38: =IF(OR(NOT(ISNUMBER(F32)),NOT(ISNUMBER(F35))),"",F32-F35) -> 564900
G39: AMOUNT CERTIFIED................................................................................................... | M39: =IF(NOT(ISNUMBER(F38)),"",F38) -> 564900
A40: 9 | B40: BALANCE TO FINISH, INCLUDING RETAINAGE | G40: (Attached explanation if amount certified differs from the amount applied for. Initial all figures on this
B41: (LINE 3 LESS LINE 6) | E41: =IF(NOT(ISNUMBER(F32)),"",F20-F32) -> 1224100 | G41: Application and on the continuation sheet that are changed to conform to the amount certified.)
G43: GENERAL CONTRACTOR
G45: By: | L45: Date:
G47: This certificate is not negotiable. The AMOUNT CERTIFIED is payable only to the Contractor named
G48: herein. Issuance, payment and acceptance of payment are without prejudice to any rights of the Owner
G49: of Contractor under this Contract.

Sheet 3_CONTINUATION SHEET
B1: CONTINUATION SHEET
T2: APPLICATION NO: | U2: 1
B3: APPLICATION AND CERTIFICATE FOR PAYMENT, | T3: APPLICATION DATE: | U3: 46285
B4: Containing Contractor's signed Certification, is attached. | T4: PERIOD TO: | U4: 09/01/26 ~ 09/30/26 (Forecast)
B5: In tabulations below, amounts are stated to the nearest dollar..
B6: Use column I on Contracts where variable retainage for line items may apply.
B8: A | C8: B | F8: C | L8: D | N8: E | P8: F | S8: G | U8: H
B9: ITEM NO. | C9: DESCRIPTION OF WORK | D9: Specification | E9: Unit | F9: CONTRACT VALUE (계약) | L9: WORK COMPLETED | P9: UP TO THIS BILL | R9: % | S9: BALANCE TO | U9: RETAINAGE
L10: PREVIOUS | N10: THIS PERIOD
F11: Quantity | G11: Material | H11: Labor | I11: Expense | J11: Unit Price | K11: Amount | L11: Quantity | M11: Amount | N11: Quantity | O11: Amount | P11: Quantity | Q11: Amount | S11: Quantity | T11: Amount
B12: 1 | C12: 건축공사 | E12: L/S | F12: 1 | K12: =TRUNC(SUM(K13:K21),2) -> 744998.1 | M12: =TRUNC(SUM(M13:M21),2) -> 0 | N12: =N49+N56+N65+N74+N84+N89+N103+N121+N169+N176+N195+N230+N264+N277+N288 -> 0 | O12: =TRUNC(SUM(O13:O21),2) -> 132127.08 | P12: =L12+N12 -> 0 | Q12: =TRUNC(SUM(Q13:Q21),2) -> 132127.08 | R12: =Q12/K12 -> 0.17735224 | T12: =TRUNC(SUM(T13:T21),2) -> 339684.89
C13: =C44 -> 1) TEMPORARY | E13: L/S | F13: 1 | K13: =K49 -> 37554 | M13: =M49 -> 0 | O13: =O49 -> 0 | Q13: =Q49 -> 0 | R13: =Q13/K13 -> 0 | T13: =T49 -> 37554
C14: =C50 -> 2) DOOR, WINDOW | E14: L/S | F14: 1 | K14: =K56 -> 25683.44 | M14: =M56 -> 0 | O14: =O56 -> 0 | Q14: =Q56 -> 0 | R14: =Q14/K14 -> 0 | T14: =T56 -> 25683.44
C15: =C57 -> 3) DRYWALL | E15: L/S | F15: 1 | K15: =K65 -> 94548.52 | M15: =M65 -> 0 | O15: =O65 -> 43909.46 | Q15: =Q65 -> 43909.46 | R15: =Q15/K15 -> 0.46441192 | T15: =T65 -> 50639.06
C16: =C66 -> 4) WALL FINISH | E16: L/S | F16: 1 | K16: =K74 -> 83277.19 | M16: =M74 -> 0 | O16: =O74 -> 0 | Q16: =Q74 -> 0 | R16: =Q16/K16 -> 0 | T16: =T74 -> 83277.19
C17: =C75 -> 5) FLOOR FINISH | E17: L/S | F17: 1 | K17: =K84 -> 67623.82 | M17: =M84 -> 0 | O17: =O84 -> 1859.6 | Q17: =Q84 -> 1859.6 | R17: =Q17/K17 -> 0.027499186 | T17: =T84 -> 65764.22
C18: =C85 -> 6) CEILING FINISH | E18: L/S | F18: 1 | K18: =K89 -> 45294 | M18: =M89 -> 0 | O18: =O89 -> 0 | Q18: =Q89 -> 0 | R18: =Q18/K18 -> 0 | T18: =T89 -> 45294
C19: =C90 -> 7) MISCELLANEOUS | E19: L/S | F19: 1 | K19: =K103 -> 193390.14 | M19: =M103 -> 0 | O19: =O103 -> 52972.812 | Q19: =Q103 -> 52972.812 | R19: =Q19/K19 -> 0.27391682 | T19: =T103 -> 16664.34
C20: =C104 -> 8) TOLIET WORKS | E20: L/S | F20: 1 | K20: =K121 -> 31845.22 | M20: =M121 -> 0 | O20: =O121 -> 0 | Q20: =Q121 -> 0 | R20: =Q20/K20 -> 0 | T20: =T121 -> 4751.72
C21: =C122 -> 9) CIVIL WORKS | E21: L/S | F21: 1 | K21: =K169 -> 165781.77 | M21: =M169 -> 0 | O21: =O169 -> 33385.211 | Q21: =Q169 -> 33385.211 | R21: =Q21/K21 -> 0.20138047 | T21: =T169 -> 10056.92
B22: 1.1 | C22: 설비공사 | E22: L/S | F22: 1 | K22: =TRUNC(SUM(K23:K31),2) -> 571271.38 | M22: =TRUNC(SUM(M23:M31),2) -> 0 | N22: =N296+N309+N339+N411+N439 -> 0 | O22: =TRUNC(SUM(O23:O31),2) -> 17851.5 | P22: =L22+N22 -> 0 | Q22: =TRUNC(SUM(Q23:Q31),2) -> 17851.5 | R22: =Q22/K22 -> 0.031248721 | T22: =TRUNC(SUM(T23:T31),2) -> 553419.87
C23: =C172 -> M0 General | D23: 74 | E23: L/S | F23: 1 | K23: =K176 -> 44319.55 | M23: =M176 -> 0 | O23: =O176 -> 0 | Q23: =Q176 -> 0 | R23: =Q23/K23 -> 0 | T23: =T176 -> 44319.55
C24: =C177 -> M1-1. Equipment | D24: 74 | E24: L/S | F24: 1 | K24: =K195 -> 31745.98 | M24: =M195 -> 0 | O24: =O195 -> 0 | Q24: =Q195 -> 0 | R24: =Q24/K24 -> 0 | T24: =T195 -> 31745.98
C25: =C196 -> M1-2. Duct Work | D25: 74 | E25: L/S | F25: 1 | K25: =K230 -> 121114.79 | M25: =M230 -> 0 | O25: =O230 -> 0 | Q25: =Q230 -> 0 | R25: =Q25/K25 -> 0 | T25: =T230 -> 121114.79
C26: =C231 -> M1-3-1. Domestic Water | D26: 74 | E26: L/S | F26: 1 | K26: =K264 -> 31293.987 | M26: =M264 -> 0 | O26: =O264 -> 6427.0832 | Q26: =Q264 -> 6427.0832 | R26: =Q26/K26 -> 0.20537758 | T26: =T264 -> 24866.904
C27: =C265 -> M1-3-2. Plumbing | E27: L/S | F27: 1 | K27: =K277 -> 8248.5435 | M27: =M277 -> 0 | O27: =O277 -> 8248.5435 | Q27: =Q277 -> 8248.5435 | R27: =Q27/K27 -> 1 | T27: =T277 -> 0
C28: =C278 -> M1-3-3 A/G NG Piping Work | E28: L/S | F28: 1 | K28: =K288 -> 7303.9099 | M28: =M288 -> 0 | O28: =O288 -> 3175.875 | Q28: =Q288 -> 3175.875 | R28: =Q28/K28 -> 0.43481847 | T28: =T288 -> 4128.035
C29: =C289 -> M1-4. Fire Protection Work | E29: L/S | F29: 1 | K29: =K296 -> 0 | M29: =M296 -> 0 | O29: =O296 -> 0 | Q29: =Q296 -> 0 | R29: =Q29/K29 -> #DIV/0! | T29: =T296 -> 0
C30: =C297 -> M1-5. Mechanical Demolition Work | E30: L/S | F30: 1 | K30: =K309 -> 26262.949 | M30: =M309 -> 0 | O30: =O309 -> 0 | Q30: =Q309 -> 0 | R30: =Q30/K30 -> 0 | T30: =T309 -> 26262.949
C31: =C310 -> M1-6. Civil WORK | E31: L/S | F31: 1 | K31: =K339 -> 300981.67 | M31: =M339 -> 0 | O31: =O339 -> 0 | Q31: =Q339 -> 0 | R31: =Q31/K31 -> 0 | T31: =T339 -> 300981.67
B32: 1.2 | C32: 전기공사 | E32: L/S | F32: 1 | K32: =TRUNC(SUM(K33:K38),2) -> 473550.88 | M32: =TRUNC(SUM(M33:M38),2) -> 0 | N32: =N458+N476+N485 -> 0 | O32: =TRUNC(SUM(O33:O38),2) -> 68365.84 | P32: =L32+N32 -> 0 | Q32: =TRUNC(SUM(Q33:Q38),2) -> 68365.84 | R32: =Q32/K32 -> 0.14436852 | T32: =TRUNC(SUM(T33:T38),2) -> 405185.04
C33: =C342 -> 01. POWER DISTRIBUTION WORK | D33: 74 | E33: L/S | F33: 1 | K33: =K411 -> 146204.14 | M33: =M411 -> 0 | O33: =O411 -> 68365.84 | Q33: =Q411 -> 68365.84 | R33: =Q33/K33 -> 0.46760536 | T33: =T411 -> 77838.3
C34: =C412 -> 02. MECHANICAL POWER WORK | D34: 74 | E34: L/S | F34: 1 | K34: =K439 -> 140971.86 | M34: =M439 -> 0 | O34: =O439 -> 0 | Q34: =Q439 -> 0 | R34: =Q34/K34 -> 0 | T34: =T439 -> 140971.86
C35: =C440 -> 03. Lighting WORK | E35: L/S | F35: 1 | K35: =K458 -> 63568.46 | M35: =M458 -> 0 | O35: =O458 -> 0 | Q35: =Q458 -> 0 | R35: =Q35/K35 -> 0 | T35: =T458 -> 63568.46
C36: =C459 -> 04. Receptacle WORK | D36: 74 | E36: L/S | F36: 1 | K36: =K476 -> 48825.62 | M36: =M476 -> 0 | O36: =O476 -> 0 | Q36: =Q476 -> 0 | R36: =Q36/K36 -> 0 | T36: =T476 -> 48825.62
C37: =C477 -> 05. INCIDENTAL EXPENSE | D37: 74 | E37: L/S | F37: 1 | K37: =K485 -> 73980.8 | M37: =M485 -> 0 | O37: =O485 -> 0 | Q37: =Q485 -> 0 | R37: =Q37/K37 -> 0 | T37: =T485 -> 73980.8
C38: =C486 -> 06. FIRE ALARM SYSTEM | D38: 74 | E38: L/S | F38: 1 | K38: =K489 -> 0 | M38: =M489 -> 0 | O38: =O489 -> 0 | Q38: =Q489 -> 0 | R38: =Q38/K38 -> #DIV/0! | T38: =T489 -> 0
C39: Round Off | K39: =-MOD(K12+K22+K32,1000) -> -820.36 | M39: =-MOD(M12+M22+M32,1000) -> 0 | O39: =-MOD(O12+O22+O32,1000) -> -344.42 | Q39: =-MOD(Q12+Q22+Q32,1000) -> -344.42
C41: TOTAL | K41: =K12+K22+K32+K39 -> 1789000 | M41: =M12+M22+M32+M39 -> 0 | O41: =O12+O22+O32+O39 -> 218000 | Q41: =Q12+Q22+Q32+Q39 -> 218000 | T41: =T12+T22+T32+T39 -> 1298289.8 | U41: =TRUNC(Q41*5%,2) -> 10900 | Z41: 1
B43: 0 | C43: 건축공사
B44: =B43+1 -> 1 | C44: 1) TEMPORARY
B45: =B44+1 -> 2 | C45: Demolition of Fence | E45: LF | F45: 200 | G45: 0 | H45: 14.11 | J45: =I45+H45+G45 -> 14.11 | K45: =J45*F45 -> 2822 | M45: =L45*J45 -> 0 | O45: =N45*J45 -> 0 | P45: =N45+L45 -> 0 | Q45: =P45*J45 -> 0 | R45: =IFERROR(Q45/K45,0) -> 0 | S45: =F45-P45 -> 200 | T45: =K45-Q45 -> 2822
B46: =B45+1 -> 3 | C46: WIRE MESHED FENCE (Permanent Fence) | D46: H:8', Incl. Footing Included, Color : RAL 9010, 6 Gauge | E46: LF | F46: 200 | G46: 33.94 | H46: 56.02 | J46: =I46+H46+G46 -> 89.96 | K46: =J46*F46 -> 17992 | M46: =L46*J46 -> 0 | O46: =N46*J46 -> 0 | P46: =N46+L46 -> 0 | Q46: =P46*J46 -> 0 | R46: =IFERROR(Q46/K46,0) -> 0 | S46: =F46-P46 -> 200 | T46: =K46-Q46 -> 17992
B47: =B46+1 -> 4 | C47: Temporary Fence - Fixed Type | D47: H=8', Galvanized Chain link fence, Including Entrance door | E47: LF | F47: 600 | G47: 10.72 | H47: 17.18 | J47: =I47+H47+G47 -> 27.9 | K47: =J47*F47 -> 16740 | M47: =L47*J47 -> 0 | O47: =N47*J47 -> 0 | P47: =N47+L47 -> 0 | Q47: =P47*J47 -> 0 | R47: =IFERROR(Q47/K47,0) -> 0 | S47: =F47-P47 -> 600 | T47: =K47-Q47 -> 16740 | W47: =M47-V47 -> 0
B48: =B47+1 -> 5
B49: =B48+1 -> 6 | C49: [ Sub Total ] | K49: =SUM(K45:K47) -> 37554 | M49: =SUM(M45:M47) -> 0 | O49: =SUM(O45:O47) -> 0 | Q49: =SUM(Q45:Q47) -> 0 | R49: =IFERROR(+Q49/K49,0) -> 0 | T49: =SUM(T45:T47) -> 37554 | W49: =M49-V49 -> 0
B50: =B49+1 -> 7 | C50: 2) DOOR, WINDOW | W50: =M50-V50 -> 0
B51: =B50+1 -> 8 | C51: SINGLE STEEL DOOR | D51: Supply and install, hollow metal frame and door, including hardware set with glass, Size: 3' X 7' | E51: EA | F51: 5 | G51: 1295.56 | H51: 927.82 | J51: =I51+H51+G51 -> 2223.38 | K51: =J51*F51 -> 11116.9 | M51: =L51*J51 -> 0 | O51: =N51*J51 -> 0 | P51: =N51+L51 -> 0 | Q51: =P51*J51 -> 0 | R51: =IFERROR(Q51/K51,0) -> 0 | S51: =F51-P51 -> 5 | T51: =K51-Q51 -> 11116.9 | W51: =M51-V51 -> 0
B52: =B51+1 -> 9 | C52: DOUBLE STEEL DOOR | D52: Supply and install, hollow metal frame and door, including hardware set with glass, Size: 6' X 7' | E52: EA | F52: 1 | G52: 2323.08 | H52: 1391.8 | J52: =I52+H52+G52 -> 3714.88 | K52: =J52*F52 -> 3714.88 | M52: =L52*J52 -> 0 | O52: =N52*J52 -> 0 | P52: =N52+L52 -> 0 | Q52: =P52*J52 -> 0 | R52: =IFERROR(Q52/K52,0) -> 0 | S52: =F52-P52 -> 1 | T52: =K52-Q52 -> 3714.88 | W52: =M52-V52 -> 0
B53: =B52+1 -> 10 | C53: SINGLE SWINGING DOOR | D53: Supply and install frame and door, including hardware set with 16" x 16" and and 1/4" glass, Size: 3' X 7' | E53: EA | F53: 1 | G53: 1518.93 | H53: 973.77 | J53: =I53+H53+G53 -> 2492.7 | K53: =J53*F53 -> 2492.7 | M53: =L53*J53 -> 0 | O53: =N53*J53 -> 0 | P53: =N53+L53 -> 0 | Q53: =P53*J53 -> 0 | R53: =IFERROR(Q53/K53,0) -> 0 | S53: =F53-P53 -> 1 | T53: =K53-Q53 -> 2492.7 | W53: =M53-V53 -> 0
B54: =B53+1 -> 11 | C54: DOUBLE SWINGING DOOR | D54: Supply and install frame and door, including hardware set with 16" x 16" and and 1/4" glass, Size: 6' X 7' | E54: EA | F54: 2 | G54: 2680.48 | H54: 1499 | J54: =I54+H54+G54 -> 4179.48 | K54: =J54*F54 -> 8358.96 | M54: =L54*J54 -> 0 | O54: =N54*J54 -> 0 | P54: =N54+L54 -> 0 | Q54: =P54*J54 -> 0 | R54: =IFERROR(Q54/K54,0) -> 0 | S54: =F54-P54 -> 2 | T54: =K54-Q54 -> 8358.96 | W54: =M54-V54 -> 0
B55: =B54+1 -> 12 | W55: =M55-V55 -> 0
B56: =B55+1 -> 13 | C56: [ Sub Total ] | K56: =SUM(K51:K55) -> 25683.44 | M56: =SUM(M51:M55) -> 0 | O56: =Q56-M56 -> 0 | Q56: =SUM(Q51:Q55) -> 0 | R56: =IFERROR(+Q56/K56,0) -> 0 | T56: =SUM(T51:T55) -> 25683.44 | W56: =M56-V56 -> 0
B57: =B56+1 -> 14 | C57: 3) DRYWALL | W57: =M57-V57 -> 0
B58: =B57+1 -> 15 | C58: Dry Wall(Water resistant) one side | D58: 1 layer Water-resistant Gypsum board + 6" C-stud O.C 16" with bridge channel + insulation | E58: LF2 | F58: 2088 | G58: 2.75 | H58: 7.24 | J58: =I58+H58+G58 -> 9.99 | K58: =J58*F58 -> 20859.12 | M58: =L58*J58 -> 0 | N58: 1044 | O58: =N58*J58 -> 10429.56 | P58: =N58+L58 -> 1044 | Q58: =P58*J58 -> 10429.56 | R58: =IFERROR(Q58/K58,0) -> 0.5 | S58: =F58-P58 -> 1044 | T58: =K58-Q58 -> 10429.56 | W58: =M58-V58 -> 0
B59: =B58+1 -> 16 | C59: Dry Wall(Water resistant) both side | D59: 1 layer Water-resistant Gypsum board + 6" C-stud O.C 16" with bridge channel + insulation + 1 layer Water-resistant Gypsum board | E59: LF2 | F59: 1885 | G59: 3.92 | H59: 9.55 | J59: =I59+H59+G59 -> 13.47 | K59: =J59*F59 -> 25390.95 | M59: =L59*J59 -> 0 | N59: 942.5 | O59: =N59*J59 -> 12695.475 | P59: =N59+L59 -> 942.5 | Q59: =P59*J59 -> 12695.475 | R59: =IFERROR(Q59/K59,0) -> 0.5 | S59: =F59-P59 -> 942.5 | T59: =K59-Q59 -> 12695.475 | W59: =M59-V59 -> 0
B60: =B59+1 -> 17 | C60: Dry Wall one side | D60: 1 layer Gypsum board + 6" C-stud O.C 16" with bridge channel + insulation | E60: LF2 | F60: 553 | G60: 2.5 | H60: 6.93 | J60: =I60+H60+G60 -> 9.43 | K60: =J60*F60 -> 5214.79 | M60: =L60*J60 -> 0 | N60: 276.5 | O60: =N60*J60 -> 2607.395 | P60: =N60+L60 -> 276.5 | Q60: =P60*J60 -> 2607.395 | R60: =IFERROR(Q60/K60,0) -> 0.5 | S60: =F60-P60 -> 276.5 | T60: =K60-Q60 -> 2607.395 | W60: =M60-V60 -> 0
B61: =B60+1 -> 18 | C61: Dry Wall both side | D61: 1 layer Gypsum board + 6" C-stud O.C 16" with bridge channel + insulation + 1 layer Gypsum board | E61: LF2 | F61: 2906 | G61: 3.57 | H61: 8.94 | J61: =I61+H61+G61 -> 12.51 | K61: =J61*F61 -> 36354.06 | M61: =L61*J61 -> 0 | N61: 1453 | O61: =N61*J61 -> 18177.03 | P61: =N61+L61 -> 1453 | Q61: =P61*J61 -> 18177.03 | R61: =IFERROR(Q61/K61,0) -> 0.5 | S61: =F61-P61 -> 1453 | T61: =K61-Q61 -> 18177.03 | W61: =M61-V61 -> 0
B62: =B61+1 -> 19 | C62: PENETRATION SEAL | D62: Seal the wall penetrations within the ceiling using fire-rated sealant or general sealant to make air-tight and sound-tight | E62: LF2 | F62: 320 | G62: 2.21 | H62: 7.68 | J62: =I62+H62+G62 -> 9.89 | K62: =J62*F62 -> 3164.8 | M62: =L62*J62 -> 0 | O62: =N62*J62 -> 0 | P62: =N62+L62 -> 0 | Q62: =P62*J62 -> 0 | R62: =IFERROR(Q62/K62,0) -> 0 | S62: =F62-P62 -> 320 | T62: =K62-Q62 -> 3164.8 | W62: =M62-V62 -> 0
B63: =B62+1 -> 20 | C63: REINFORCEMENT FOR DRY WALL | D63: Reinforcement of structure for Dry wall around the opening caused by mechanical, eletrical, other works | E63: LF2 | F63: 320 | G63: 2.67 | H63: 8.47 | J63: =I63+H63+G63 -> 11.14 | K63: =J63*F63 -> 3564.8 | M63: =L63*J63 -> 0 | O63: =N63*J63 -> 0 | P63: =N63+L63 -> 0 | Q63: =P63*J63 -> 0 | R63: =IFERROR(Q63/K63,0) -> 0 | S63: =F63-P63 -> 320 | T63: =K63-Q63 -> 3564.8 | W63: =M63-V63 -> 0
B64: =B63+1 -> 21 | W64: =M64-V64 -> 0
B65: =B64+1 -> 22 | C65: [ Sub Total ] | K65: =SUM(K58:K63) -> 94548.52 | M65: =SUM(M58:M63) -> 0 | O65: =Q65-M65 -> 43909.46 | Q65: =SUM(Q58:Q64) -> 43909.46 | R65: =IFERROR(+Q65/K65,0) -> 0.46441192 | T65: =SUM(T58:T64) -> 50639.06 | W65: =M65-V65 -> 0
B66: =B65+1 -> 23 | C66: 4) WALL FINISH | W66: =M66-V66 -> 0
B67: =B66+1 -> 24 | C67: Water Paint | D67: Primer(1 coat) + Top Coat(2 Coats), Joint and surface treatment included. Color : RAL 9010/9006 and Varied | E67: LF2 | F67: 6182 | G67: 0.48 | H67: 2.31 | J67: =I67+H67+G67 -> 2.79 | K67: =J67*F67 -> 17247.78 | M67: =L67*J67 -> 0 | O67: =N67*J67 -> 0 | P67: =N67+L67 -> 0 | Q67: =P67*J67 -> 0 | R67: =IFERROR(Q67/K67,0) -> 0 | S67: =F67-P67 -> 6182 | T67: =K67-Q67 -> 17247.78 | W67: =M67-V67 -> 0
B68: =B67+1 -> 25 | C68: Stainless Steel Wall | D68: THK : 3/8", Grade 316, Epoxy adhesive, edge/corner treatment(rounded),mirror finish,joint welding included | E68: LF2 | F68: 311 | G68: 46.53 | H68: 51.11 | J68: =I68+H68+G68 -> 97.64 | K68: =J68*F68 -> 30366.04 | M68: =L68*J68 -> 0 | O68: =N68*J68 -> 0 | P68: =N68+L68 -> 0 | Q68: =P68*J68 -> 0 | R68: =IFERROR(Q68/K68,0) -> 0 | S68: =F68-P68 -> 311 | T68: =K68-Q68 -> 30366.04 | W68: =M68-V68 -> 0
B69: =B68+1 -> 26 | C69: Polyurethane Liquid Membrane Waterproofing(Kitchen) | D69: Wall, Include Surface treatment and chamfer/patch up. Apply floors and walls Ponding test(min 24 hrs) required | E69: LF2 | F69: 1019 | G69: 2.86 | H69: 7.37 | J69: =I69+H69+G69 -> 10.23 | K69: =J69*F69 -> 10424.37 | M69: =L69*J69 -> 0 | O69: =N69*J69 -> 0 | P69: =N69+L69 -> 0 | Q69: =P69*J69 -> 0 | R69: =IFERROR(Q69/K69,0) -> 0 | S69: =F69-P69 -> 1019 | T69: =K69-Q69 -> 10424.37 | W69: =M69-V69 -> 0
B70: =B69+1 -> 27 | C70: Stainless Steel Base | D70: Supply an install 4" high Stainless steel plate base on walls | E70: LF | F70: 231.25 | G70: 8.04 | H70: 13.88 | J70: =I70+H70+G70 -> 21.92 | K70: =J70*F70 -> 5069 | M70: =L70*J70 -> 0 | O70: =N70*J70 -> 0 | P70: =N70+L70 -> 0 | Q70: =P70*J70 -> 0 | R70: =IFERROR(Q70/K70,0) -> 0 | S70: =F70-P70 -> 231.25 | T70: =K70-Q70 -> 5069 | W70: =M70-V70 -> 0
B71: =B70+1 -> 28 | C71: FRP Panel | D71: Fiber Reinforced Plastic Panel | E71: LF2 | F71: 1500 | G71: 3.03 | H71: 5.37 | J71: =I71+H71+G71 -> 8.4 | K71: =J71*F71 -> 12600 | M71: =L71*J71 -> 0 | O71: =N71*J71 -> 0 | P71: =N71+L71 -> 0 | Q71: =P71*J71 -> 0 | R71: =IFERROR(Q71/K71,0) -> 0 | S71: =F71-P71 -> 1500 | T71: =K71-Q71 -> 12600 | W71: =M71-V71 -> 0
B72: =B71+1 -> 29 | C72: PVC Panel | D72: Moisture resistance | E72: LF2 | F72: 1000 | G72: 2.5 | H72: 5.07 | J72: =I72+H72+G72 -> 7.57 | K72: =J72*F72 -> 7570 | M72: =L72*J72 -> 0 | O72: =N72*J72 -> 0 | P72: =N72+L72 -> 0 | Q72: =P72*J72 -> 0 | R72: =IFERROR(Q72/K72,0) -> 0 | S72: =F72-P72 -> 1000 | T72: =K72-Q72 -> 7570 | W72: =M72-V72 -> 0
B73: =B72+1 -> 30 | W73: =M73-V73 -> 0
B74: =B73+1 -> 31 | C74: [ Sub Total ] | K74: =SUM(K67:K73) -> 83277.19 | M74: =SUM(M67:M73) -> 0 | O74: =Q74-M74 -> 0 | Q74: =SUM(Q67:Q73) -> 0 | R74: =IFERROR(+Q74/K74,0) -> 0 | T74: =SUM(T67:T73) -> 83277.19 | W74: =M74-V74 -> 0
B75: =B74+1 -> 32 | C75: 5) FLOOR FINISH | W75: =M75-V75 -> 0
B76: =B75+1 -> 33 | C76: Concrete Demolition of less than 2CY at once | D76: Perimeter wall,Reinforcement bar cutting and cutting surfrace treatement and rubbish disposal included | E76: YD3 | F76: 10 | G76: 0 | H76: 785.93 | J76: =I76+H76+G76 -> 785.93 | K76: =J76*F76 -> 7859.3 | M76: =L76*J76 -> 0 | O76: =N76*J76 -> 0 | P76: =N76+L76 -> 0 | Q76: =P76*J76 -> 0 | R76: =IFERROR(Q76/K76,0) -> 0 | S76: =F76-P76 -> 10 | T76: =K76-Q76 -> 7859.3 | W76: =M76-V76 -> 0
B77: =B76+1 -> 34 | C77: Floor concrete | D77: 2500 psi, premixed concrete, Supplying material, Pouring and vibrating, Leveling, including formwork and all submaterials. Machine trowel & manual steel trowel where machine cannot enter, w/ chamfered edge at pads & exposed structures, including all necessary works and submaterials. | E77: YD3 | F77: 2 | G77: 196.54 | H77: 733.26 | J77: =I77+H77+G77 -> 929.8 | K77: =J77*F77 -> 1859.6 | M77: =L77*J77 -> 0 | N77: 2 | O77: =N77*J77 -> 1859.6 | P77: =N77+L77 -> 2 | Q77: =P77*J77 -> 1859.6 | R77: =IFERROR(Q77/K77,0) -> 1 | S77: =F77-P77 -> 0 | T77: =K77-Q77 -> 0 | W77: =M77-V77 -> 0
B78: =B77+1 -> 35 | C78: Reinforcement Bars | D78: #3, #4, #5, #6, #7, #8, #9. etc. | E78: TON | F78: 1 | G78: 1295.56 | H78: 2013.36 | J78: =I78+H78+G78 -> 3308.92 | K78: =J78*F78 -> 3308.92 | M78: =L78*J78 -> 0 | O78: =N78*J78 -> 0 | P78: =N78+L78 -> 0 | Q78: =P78*J78 -> 0 | R78: =IFERROR(Q78/K78,0) -> 0 | S78: =F78-P78 -> 1 | T78: =K78-Q78 -> 3308.92 | W78: =M78-V78 -> 0
B79: =B78+1 -> 36 | C79: Ucrete Polyurethane Coating | D79: Include cocnrete floor grinding and all requirements recommended by the manufacturer. Color will be applied. BASF UCRETE DP or equivalent | E79: LF2 | F79: 1800 | G79: 6.69 | H79: 9.72 | J79: =I79+H79+G79 -> 16.41 | K79: =J79*F79 -> 29538 | M79: =L79*J79 -> 0 | O79: =N79*J79 -> 0 | P79: =N79+L79 -> 0 | Q79: =P79*J79 -> 0 | R79: =IFERROR(Q79/K79,0) -> 0 | S79: =F79-P79 -> 1800 | T79: =K79-Q79 -> 29538 | W79: =M79-V79 -> 0
B80: =B79+1 -> 37 | C80: Floor surface preparation and protection work | E80: LF2 | F80: 1800 | G80: 1.06 | H80: 4.63 | J80: =I80+H80+G80 -> 5.69 | K80: =J80*F80 -> 10242 | M80: =L80*J80 -> 0 | O80: =N80*J80 -> 0 | P80: =N80+L80 -> 0 | Q80: =P80*J80 -> 0 | R80: =IFERROR(Q80/K80,0) -> 0 | S80: =F80-P80 -> 1800 | T80: =K80-Q80 -> 10242 | W80: =M80-V80 -> 0
B81: =B80+1 -> 38 | C81: Epoxy Coating | D81: Primer + Epoxy Coating | E81: LF2 | F81: 1800 | G81: 1.96 | H81: 4.61 | J81: =I81+H81+G81 -> 6.57 | K81: =J81*F81 -> 11826 | M81: =L81*J81 -> 0 | O81: =N81*J81 -> 0 | P81: =N81+L81 -> 0 | Q81: =P81*J81 -> 0 | R81: =IFERROR(Q81/K81,0) -> 0 | S81: =F81-P81 -> 1800 | T81: =K81-Q81 -> 11826 | W81: =M81-V81 -> 0
B82: =B81+1 -> 39 | C82: Vinyl Composite Tile | D82: Supply and install Armstrong Premium Excelon Raffia Stream or equivalent. Include adhesive and misc. materials. Surface treatment included. Material grade shall be Luxury Vinyl Tile. 2 times floor waxing included. | E82: LF2 | F82: 200 | G82: 3.57 | H82: 11.38 | J82: =I82+H82+G82 -> 14.95 | K82: =J82*F82 -> 2990 | M82: =L82*J82 -> 0 | O82: =N82*J82 -> 0 | P82: =N82+L82 -> 0 | Q82: =P82*J82 -> 0 | R82: =IFERROR(Q82/K82,0) -> 0 | S82: =F82-P82 -> 200 | T82: =K82-Q82 -> 2990 | W82: =M82-V82 -> 0
B83: =B82+1 -> 40 | W83: =M83-V83 -> 0
B84: =B83+1 -> 41 | C84: [ Sub Total ] | K84: =SUM(K76:K83) -> 67623.82 | M84: =SUM(M76:M83) -> 0 | O84: =Q84-M84 -> 1859.6 | Q84: =SUM(Q76:Q83) -> 1859.6 | R84: =IFERROR(+Q84/K84,0) -> 0.027499186 | T84: =SUM(T76:T83) -> 65764.22 | W84: =M84-V84 -> 0
B85: =B84+1 -> 42 | C85: 6) CEILING FINISH | W85: =M85-V85 -> 0
B86: =B85+1 -> 43 | C86: Acoustic Ceiling Tile | D86: Supply and install 2'X2' USG-HALCYON or equivalent. Ceiling panels for Narrow Grid, include thred bolt supported and t-bar grid system including required accessories and misc. materials | E86: LF2 | F86: 640 | G86: 3.74 | H86: 6.31 | J86: =I86+H86+G86 -> 10.05 | K86: =J86*F86 -> 6432 | M86: =L86*J86 -> 0 | O86: =N86*J86 -> 0 | P86: =N86+L86 -> 0 | Q86: =P86*J86 -> 0 | R86: =IFERROR(Q86/K86,0) -> 0 | S86: =F86-P86 -> 640 | T86: =K86-Q86 -> 6432 | W86: =M86-V86 -> 0
B87: =B86+1 -> 44 | C87: SMC Ceiling Tile | D87: Supply and install SMC ceiling including all steel structure support and clip-bar,channels and hangers and all accessories required for installation. | E87: LF2 | F87: 1800 | G87: 8.48 | H87: 13.11 | J87: =I87+H87+G87 -> 21.59 | K87: =J87*F87 -> 38862 | M87: =L87*J87 -> 0 | O87: =N87*J87 -> 0 | P87: =N87+L87 -> 0 | Q87: =P87*J87 -> 0 | R87: =IFERROR(Q87/K87,0) -> 0 | S87: =F87-P87 -> 1800 | T87: =K87-Q87 -> 38862 | W87: =M87-V87 -> 0
B88: =B87+1 -> 45 | W88: =M88-V88 -> 0
B89: =B88+1 -> 46 | C89: [ Sub Total ] | K89: =SUM(K86:K88) -> 45294 | M89: =SUM(M86:M88) -> 0 | O89: =Q89-M89 -> 0 | Q89: =SUM(Q86:Q88) -> 0 | R89: =IFERROR(+Q89/K89,0) -> 0 | T89: =SUM(T86:T88) -> 45294 | W89: =M89-V89 -> 0
B90: =B89+1 -> 47 | C90: 7) MISCELLANEOUS | W90: =M90-V90 -> 0
B91: =B90+1 -> 48 | C91: Bollard Demolition | E91: EA | F91: 7 | G91: 0 | H91: 244.11 | J91: =I91+H91+G91 -> 244.11 | K91: =J91*F91 -> 1708.77 | M91: =L91*J91 -> 0 | O91: =N91*J91 -> 0 | P91: =N91+L91 -> 0 | Q91: =P91*J91 -> 0 | R91: =IFERROR(Q91/K91,0) -> 0 | S91: =F91-P91 -> 7 | T91: =K91-Q91 -> 1708.77 | W91: =M91-V91 -> 0
B92: =B91+1 -> 49 | C92: Grease Trap(Grease Interceptor) | D92: Capacity : 1,500 GL, Include all electric cable&conduit wiring,clean-out drain,connection between the sample well and clean-out drain. Main DB panel and Service alert panel connection, all concrete structures and elements composing of Grease interceptor system. all civi works(excavation,GAB grading and compaction, Lean concrete), referring to Dwg 410-A-901 | E92: SET | F92: 2 | G92: 22516.08 | H92: 39297.34 | J92: =I92+H92+G92 -> 61813.42 | K92: =J92*F92 -> 123626.84 | M92: =L92*J92 -> 0 | N92: 0.6 | O92: =N92*J92 -> 37088.052 | P92: =N92+L92 -> 0.6 | Q92: =P92*J92 -> 37088.052 | R92: =IFERROR(Q92/K92,0) -> 0.3 | S92: =F92-P92 -> 1.4 | T92: =K92-Q92 -> 86538.788 | W92: =M92-V92 -> 0
B93: =B92+1 -> 50 | C93: Reinforcement (Roof Opening) | D93: Refer to Section & Details for site modification work for reinforcement. Modification of Existing Steel Structure Member to enable New Strucutures such as Girth, Truss, Angle and Etc. to be able to be instllaed and connected without obstuction. - Cutting off any obsturcting structure and materials - Re-Instatement of cutted off materials and structure - Welding & Touch Up Paint also Included - All Accessories necessary required also Included - Erection by using of Crane & Boom lift included | E93: TON | F93: 1 | G93: 2859.17 | H93: 13025.59 | J93: =I93+H93+G93 -> 15884.76 | K93: =J93*F93 -> 15884.76 | M93: =L93*J93 -> 0 | N93: 1 | O93: =N93*J93 -> 15884.76 | P93: =N93+L93 -> 1 | Q93: =P93*J93 -> 15884.76 | R93: =IFERROR(Q93/K93,0) -> 1 | S93: =F93-P93 -> 0 | T93: =K93-Q93 -> 0 | W93: =M93-V93 -> 0
B94: =B93+1 -> 51 | C94: Remove Existing Roof Deck | D94: Remove existing Roof Deck, incl. disposal to out of site | E94: LF2 | F94: 100 | G94: 0.43 | H94: 10.16 | J94: =I94+H94+G94 -> 10.59 | K94: =J94*F94 -> 1059 | M94: =L94*J94 -> 0 | O94: =N94*J94 -> 0 | P94: =N94+L94 -> 0 | Q94: =P94*J94 -> 0 | R94: =IFERROR(Q94/K94,0) -> 0 | S94: =F94-P94 -> 100 | T94: =K94-Q94 -> 1059 | W94: =M94-V94 -> 0
B95: =B94+1 -> 52 | C95: TPO Patch | D95: Membrane 60mil TPO | E95: LF2 | F95: 300 | G95: 3.12 | H95: 8.5 | J95: =I95+H95+G95 -> 11.62 | K95: =J95*F95 -> 3486 | M95: =L95*J95 -> 0 | O95: =N95*J95 -> 0 | P95: =N95+L95 -> 0 | Q95: =P95*J95 -> 0 | R95: =IFERROR(Q95/K95,0) -> 0 | S95: =F95-P95 -> 300 | T95: =K95-Q95 -> 3486 | W95: =M95-V95 -> 0
B96: =B95+1 -> 53 | C96: Miscellaneous Steel works | D96: Supply and installation of Structural Reinforcement steel for Canopy, Incl. Structural Calculations | E96: TON | F96: 1 | G96: 3395.28 | H96: 7366.35 | J96: =I96+H96+G96 -> 10761.63 | K96: =J96*F96 -> 10761.63 | M96: =L96*J96 -> 0 | O96: =N96*J96 -> 0 | P96: =N96+L96 -> 0 | Q96: =P96*J96 -> 0 | R96: =IFERROR(Q96/K96,0) -> 0 | S96: =F96-P96 -> 1 | T96: =K96-Q96 -> 10761.63 | W96: =M96-V96 -> 0
B97: =B96+1 -> 54 | C97: CANOPY | D97: Supply and install Vestibule Canopy(size 14'x5'x3', ACM) including the sub-structure, inlet, downspout, aluminum ceiling tile, roof membrane and other accessories for installation | E97: EA | F97: 1 | G97: 8488.19 | H97: 11710.61 | J97: =I97+H97+G97 -> 20198.8 | K97: =J97*F97 -> 20198.8 | M97: =L97*J97 -> 0 | O97: =N97*J97 -> 0 | P97: =N97+L97 -> 0 | Q97: =P97*J97 -> 0 | R97: =IFERROR(Q97/K97,0) -> 0 | S97: =F97-P97 -> 1 | T97: =K97-Q97 -> 20198.8 | W97: =M97-V97 -> 0
B98: =B97+1 -> 55 | C98: Grating | D98: For Trench, 1 3/4"x3/16" MTL BAR Grating(Galv.) | E98: LF2 | F98: 55 | G98: 25.01 | H98: 21.66 | J98: =I98+H98+G98 -> 46.67 | K98: =J98*F98 -> 2566.85 | M98: =L98*J98 -> 0 | O98: =N98*J98 -> 0 | P98: =N98+L98 -> 0 | Q98: =P98*J98 -> 0 | R98: =IFERROR(Q98/K98,0) -> 0 | S98: =F98-P98 -> 55 | T98: =K98-Q98 -> 2566.85 | W98: =M98-V98 -> 0
B99: =B98+1 -> 56 | C99: Trench-1 | D99: W36" X H6", embedded steel profiles(incl. angle), all sub-material. | E99: LF | F99: 11 | G99: 196.54 | H99: 496.8 | J99: =I99+H99+G99 -> 693.34 | K99: =J99*F99 -> 7626.74 | M99: =L99*J99 -> 0 | O99: =N99*J99 -> 0 | P99: =N99+L99 -> 0 | Q99: =P99*J99 -> 0 | R99: =IFERROR(Q99/K99,0) -> 0 | S99: =F99-P99 -> 11 | T99: =K99-Q99 -> 7626.74 | W99: =M99-V99 -> 0
B100: =B99+1 -> 57 | C100: Trench-2 | D100: W16" X H6", embedded steel profiles(incl. angle), all sub-material. | E100: LF | F100: 5 | G100: 134.02 | H100: 388.45 | J100: =I100+H100+G100 -> 522.47 | K100: =J100*F100 -> 2612.35 | M100: =L100*J100 -> 0 | O100: =N100*J100 -> 0 | P100: =N100+L100 -> 0 | Q100: =P100*J100 -> 0 | R100: =IFERROR(Q100/K100,0) -> 0 | S100: =F100-P100 -> 5 | T100: =K100-Q100 -> 2612.35 | W100: =M100-V100 -> 0
B101: =B100+1 -> 58 | C101: Trench-3 | D101: W19" X H6", embedded steel profiles(incl. angle), all sub-material. | E101: LF | F101: 7 | G101: 147.42 | H101: 403.78 | J101: =I101+H101+G101 -> 551.2 | K101: =J101*F101 -> 3858.4 | M101: =L101*J101 -> 0 | O101: =N101*J101 -> 0 | P101: =N101+L101 -> 0 | Q101: =P101*J101 -> 0 | R101: =IFERROR(Q101/K101,0) -> 0 | S101: =F101-P101 -> 7 | T101: =K101-Q101 -> 3858.4 | W101: =M101-V101 -> 0
B102: =B101+1 -> 59 | W102: =M102-V102 -> 0
B103: =B102+1 -> 60 | C103: [ Sub Total ] | K103: =SUM(K91:K102) -> 193390.14 | M103: =SUM(M98:M102) -> 0 | O103: =Q103-M103 -> 52972.812 | Q103: =SUM(Q91:Q102) -> 52972.812 | R103: =IFERROR(+Q103/K103,0) -> 0.27391682 | T103: =SUM(T98:T102) -> 16664.34 | W103: =M103-V103 -> 0
...
